Metadata-Version: 1.0
Name: distributions-rajeev
Version: 0.1
Summary: Gaussian + Binomial distributions
Home-page: UNKNOWN
Author: Rajeev Jhaj
Author-email: me@rajeevj.co.uk
License: UNKNOWN
Platform: UNKNOWN
